ttmr/__init__.py
ttmr/cli.py
ttmr/clic.py
ttmr/commands/__init__.py
ttmr/commands/entry.py
ttmr/commands/new.py
ttmr/commands/report.py
ttmr/commands/util.py
ttmr/config.py
ttmr/console.py
ttmr/database.py
ttmr/gui.py
ttmr/resources/__init__.py
ttmr/resources/week_summary.sql
ttmr/sql/INITIALIZE.sql
ttmr/sql/INSERT-CATEGORY.sql
ttmr/sql/INSERT-ENTRY.sql
ttmr/sql/INSERT-INCIDENT.sql
ttmr/sql/SELECT-ENTRY-VIEW.sql
ttmr/sql/SELECT-WEEK-SUMMARY.sql
ttmr/sql/UPDATE-ENTRY-DURATION.sql
ttmr/sql/UPDATE-ENTRY.sql
ttmr/time.py
ttmr/util.py
ttmr-0.5.15.dist-info/entry_points.txt
ttmr-0.5.15.dist-info/WHEEL
ttmr-0.5.15.dist-info/METADATA
ttmr-0.5.15.dist-info/RECORD
