Metadata-Version: 2.1
Name: ttmr
Version: 0.5.15
Summary: 
Author: Mark Gemmill
Author-email: gitlab@markgemmill.com
Requires-Python: >=3.7,<4.0
Classifier: Programming Language :: Python :: 3
Classifier: Programming Language :: Python :: 3.7
Classifier: Programming Language :: Python :: 3.8
Requires-Dist: appdirs (>=1.4.3,<2.0.0)
Requires-Dist: arrow (>=0.15.5,<0.16.0)
Requires-Dist: colorama (>=0.4.1,<0.5.0)
Requires-Dist: csvy (>=0.1.0-alpha.0,<0.2.0)
Requires-Dist: dbus-python (>=1.2.16,<2.0.0); sys_platform == "linux"
Requires-Dist: docopt-ng (>=0.7.2,<0.8.0)
Requires-Dist: pendulum (>=2.0.5,<3.0.0)
Requires-Dist: plyer (>=1.4.2,<2.0.0)
Requires-Dist: prompt-toolkit (>=3.0.3,<4.0.0)
Requires-Dist: pytest-cov (>=2.8.1,<3.0.0)
Requires-Dist: python-dateutil (>=2.8.1,<3.0.0)
Requires-Dist: sqlalchemy (>=1.3.13,<2.0.0)
Requires-Dist: tabulate (>=0.8.6,<0.9.0)
Requires-Dist: tomlkit (>=0.5.8,<0.6.0)
Requires-Dist: typer (>=0.1.0,<0.2.0)
